sdesk/__init__.py
sdesk/api/__init__.py
sdesk/api/auth.py
sdesk/api/client.py
sdesk/api/resources.py
sdesk/proc/io.py
sdesk/proc/sdesk_file.py
sdesk-0.2.3.dist-info/entry_points.txt
sdesk-0.2.3.dist-info/WHEEL
sdesk-0.2.3.dist-info/METADATA
sdesk-0.2.3.dist-info/RECORD
